{
    "metadata": {
        "celebrated": "2020-03-13T00:00:00.000Z",
        "debate": "CONVALIDACI\u00d3N O DEROGACI\u00d3N DE REALES DECRETOS-LEYES. (VOTACI\u00d3N): -- REAL DECRET O-LEY 15/2020, DE 21 DE ABRIL, DE MEDIDAS URGENTES COMPLEMENT ARIAS PARA APOYAR LA ECONOM\u00cdA Y EL EMPLEO. ",
        "diputado": [
            {
                "apellidos": "Espinosa de los Monteros de Sim\u00f3n",
                "apellidosNombre": "Espinosa de los Monteros de Sim\u00f3n, Iv\u00e1n",
                "codParlamentario": 83,
                "fchAlta": "20/11/2019",
                "fchBaja": "",
                "formacion": "Vox",
                "genero": 1,
                "grupo": "Grupo Parlamentario VOX",
                "idCircunscripcion": 28,
                "idLegislatura": 14,
                "nombre": "Iv\u00e1n",
                "nombreCircunscripcion": "Madrid",
                "twitter": "https://twitter.com/ivanedlm",
                "twitterUserId": "48976307",
                "twitterUserName": "ivanedlm"
            },
            0
        ],
        "order": 28,
        "path": "../data/diaries-txts/DSCD-14-PL-022.txt",
        "president": "MERITXELL BATET LAMA\u00d1A",
        "presidentTreatment": "Presidenta",
        "speacker": "ESPINOSA DE LOS MONTEROS DE SIM\u00d3N"
    },
    "text": "Pues vamos a ir terminando. Como entonces, el problema que hoy tenemos est\u00e1 identificado con su l\u00edder, que se llama Pedro S\u00e1nchez. Se\u00f1or\u00edas, no tengo ninguna duda de que hoy tambi\u00e9n la naci\u00f3n espa\u00f1ola est\u00e1 preparada para escribir una historia de recuperaci\u00f3n y \u00e9xito, pero eso solo ser\u00e1 posible si hay liderazgo moral, si se les dice la verdad a los espa\u00f1oles y se pone a los mejores a servir a Espa\u00f1a. Por eso, hoy es un deber de justicia pedir a quienes no est\u00e1n en condiciones de liderar la reconstrucci\u00f3n que se vayan, y ese sacrificio ser\u00e1 el que mejor puedan rendir a Espa\u00f1a. Muchas gracias. (Aplausos).",
    "freeling": [
        {
            "word": "Pues",
            "lema": "pues",
            "pos": "CS",
            "prob": "0.999049"
        },
        {
            "word": "vamos",
            "lema": "ir",
            "pos": "VMIP1P0",
            "prob": "0.965015"
        },
        {
            "word": "a",
            "lema": "a",
            "pos": "SP",
            "prob": "0.998775"
        },
        {
            "word": "ir",
            "lema": "ir",
            "pos": "VMN0000",
            "prob": "1"
        },
        {
            "word": "terminando",
            "lema": "terminar",
            "pos": "VMG0000",
            "prob": "1"
        },
        {
            "word": ".",
            "lema": ".",
            "pos": "Fp",
            "prob": "1"
        },
        {
            "word": "Como",
            "lema": "como",
            "pos": "CS",
            "prob": "0.967153"
        },
        {
            "word": "entonces",
            "lema": "entonces",
            "pos": "RG",
            "prob": "0.998203"
        },
        {
            "word": ",",
            "lema": ",",
            "pos": "Fc",
            "prob": "1"
        },
        {
            "word": "el",
            "lema": "el",
            "pos": "DA0MS0",
            "prob": "1"
        },
        {
            "word": "problema",
            "lema": "problema",
            "pos": "NCMS000",
            "prob": "1"
        },
        {
            "word": "que",
            "lema": "que",
            "pos": "PR0CN00",
            "prob": "0.550139"
        },
        {
            "word": "hoy",
            "lema": "hoy",
            "pos": "RG",
            "prob": "0.993864"
        },
        {
            "word": "tenemos",
            "lema": "tener",
            "pos": "VMIP1P0",
            "prob": "1"
        },
        {
            "word": "est\u00e1",
            "lema": "estar",
            "pos": "VMIP3S0",
            "prob": "0.999398"
        },
        {
            "word": "identificado",
            "lema": "identificar",
            "pos": "VMP00SM",
            "prob": "1"
        },
        {
            "word": "con",
            "lema": "con",
            "pos": "SP",
            "prob": "1"
        },
        {
            "word": "su",
            "lema": "su",
            "pos": "DP3CSN",
            "prob": "1"
        },
        {
            "word": "l\u00edder",
            "lema": "l\u00edder",
            "pos": "NCCS000",
            "prob": "1"
        },
        {
            "word": ",",
            "lema": ",",
            "pos": "Fc",
            "prob": "1"
        },
        {
            "word": "que",
            "lema": "que",
            "pos": "PR0CN00",
            "prob": "0.550139"
        },
        {
            "word": "se",
            "lema": "se",
            "pos": "P00CN00",
            "prob": "0.494509"
        },
        {
            "word": "llama",
            "lema": "llamar",
            "pos": "VMIP3S0",
            "prob": "0.921569"
        },
        {
            "word": "Pedro_S\u00e1nchez",
            "lema": "pedro_s\u00e1nchez",
            "pos": "NP00SP0",
            "prob": "1"
        },
        {
            "word": ".",
            "lema": ".",
            "pos": "Fp",
            "prob": "1"
        },
        {
            "word": "Se\u00f1or\u00edas",
            "lema": "se\u00f1or\u00eda",
            "pos": "NCFP000",
            "prob": "1"
        },
        {
            "word": ",",
            "lema": ",",
            "pos": "Fc",
            "prob": "1"
        },
        {
            "word": "no",
            "lema": "no",
            "pos": "RN",
            "prob": "0.999297"
        },
        {
            "word": "tengo",
            "lema": "tener",
            "pos": "VMIP1S0",
            "prob": "1"
        },
        {
            "word": "ninguna",
            "lema": "ninguno",
            "pos": "DI0FS0",
            "prob": "0.829392"
        },
        {
            "word": "duda",
            "lema": "duda",
            "pos": "NCFS000",
            "prob": "0.72549"
        },
        {
            "word": "de",
            "lema": "de",
            "pos": "SP",
            "prob": "0.999961"
        },
        {
            "word": "que",
            "lema": "que",
            "pos": "PR0CN00",
            "prob": "0.550139"
        },
        {
            "word": "hoy",
            "lema": "hoy",
            "pos": "RG",
            "prob": "0.993864"
        },
        {
            "word": "tambi\u00e9n",
            "lema": "tambi\u00e9n",
            "pos": "RG",
            "prob": "1"
        },
        {
            "word": "la",
            "lema": "el",
            "pos": "DA0FS0",
            "prob": "0.98926"
        },
        {
            "word": "naci\u00f3n",
            "lema": "naci\u00f3n",
            "pos": "NCFS000",
            "prob": "1"
        },
        {
            "word": "espa\u00f1ola",
            "lema": "espa\u00f1ol",
            "pos": "AQ0FS00",
            "prob": "0.9614"
        },
        {
            "word": "est\u00e1",
            "lema": "estar",
            "pos": "VMIP3S0",
            "prob": "0.999398"
        },
        {
            "word": "preparada",
            "lema": "preparar",
            "pos": "VMP00SF",
            "prob": "1"
        },
        {
            "word": "para",
            "lema": "para",
            "pos": "SP",
            "prob": "0.999834"
        },
        {
            "word": "escribir",
            "lema": "escribir",
            "pos": "VMN0000",
            "prob": "1"
        },
        {
            "word": "una",
            "lema": "uno",
            "pos": "DI0FS0",
            "prob": "0.951973"
        },
        {
            "word": "historia",
            "lema": "historia",
            "pos": "NCFS000",
            "prob": "1"
        },
        {
            "word": "de",
            "lema": "de",
            "pos": "SP",
            "prob": "0.999961"
        },
        {
            "word": "recuperaci\u00f3n",
            "lema": "recuperaci\u00f3n",
            "pos": "NCFS000",
            "prob": "1"
        },
        {
            "word": "y",
            "lema": "y",
            "pos": "CC",
            "prob": "0.999989"
        },
        {
            "word": "\u00e9xito",
            "lema": "\u00e9xito",
            "pos": "NCMS000",
            "prob": "1"
        },
        {
            "word": ",",
            "lema": ",",
            "pos": "Fc",
            "prob": "1"
        },
        {
            "word": "pero",
            "lema": "pero",
            "pos": "CC",
            "prob": "0.999902"
        },
        {
            "word": "eso",
            "lema": "ese",
            "pos": "PD00S00",
            "prob": "1"
        },
        {
            "word": "solo",
            "lema": "solo",
            "pos": "RG",
            "prob": "0.210162"
        },
        {
            "word": "ser\u00e1",
            "lema": "ser",
            "pos": "VSIF3S0",
            "prob": "1"
        },
        {
            "word": "posible",
            "lema": "posible",
            "pos": "AQ0CS00",
            "prob": "1"
        },
        {
            "word": "si",
            "lema": "si",
            "pos": "CS",
            "prob": "0.999827"
        },
        {
            "word": "hay",
            "lema": "haber",
            "pos": "VMIP3S0",
            "prob": "1"
        },
        {
            "word": "liderazgo",
            "lema": "liderazgo",
            "pos": "NCMS000",
            "prob": "1"
        },
        {
            "word": "moral",
            "lema": "moral",
            "pos": "AQ0CS00",
            "prob": "0.519841"
        },
        {
            "word": ",",
            "lema": ",",
            "pos": "Fc",
            "prob": "1"
        },
        {
            "word": "si",
            "lema": "si",
            "pos": "CS",
            "prob": "0.999827"
        },
        {
            "word": "se",
            "lema": "se",
            "pos": "P00CN00",
            "prob": "0.494509"
        },
        {
            "word": "les",
            "lema": "le",
            "pos": "PP3CPD0",
            "prob": "1"
        },
        {
            "word": "dice",
            "lema": "decir",
            "pos": "VMIP3S0",
            "prob": "1"
        },
        {
            "word": "la",
            "lema": "el",
            "pos": "DA0FS0",
            "prob": "0.98926"
        },
        {
            "word": "verdad",
            "lema": "verdad",
            "pos": "NCFS000",
            "prob": "1"
        },
        {
            "word": "a",
            "lema": "a",
            "pos": "SP",
            "prob": "0.998775"
        },
        {
            "word": "los",
            "lema": "el",
            "pos": "DA0MP0",
            "prob": "0.992728"
        },
        {
            "word": "espa\u00f1oles",
            "lema": "espa\u00f1ol",
            "pos": "NCMP000",
            "prob": "0.413379"
        },
        {
            "word": "y",
            "lema": "y",
            "pos": "CC",
            "prob": "0.999989"
        },
        {
            "word": "se",
            "lema": "se",
            "pos": "P00CN00",
            "prob": "0.494509"
        },
        {
            "word": "pone",
            "lema": "poner",
            "pos": "VMIP3S0",
            "prob": "1"
        },
        {
            "word": "a",
            "lema": "a",
            "pos": "SP",
            "prob": "0.998775"
        },
        {
            "word": "los",
            "lema": "el",
            "pos": "DA0MP0",
            "prob": "0.992728"
        },
        {
            "word": "mejores",
            "lema": "mejor",
            "pos": "AQ0CP00",
            "prob": "0.997685"
        },
        {
            "word": "a",
            "lema": "a",
            "pos": "SP",
            "prob": "0.998775"
        },
        {
            "word": "servir",
            "lema": "servir",
            "pos": "VMN0000",
            "prob": "1"
        },
        {
            "word": "a",
            "lema": "a",
            "pos": "SP",
            "prob": "0.998775"
        },
        {
            "word": "Espa\u00f1a",
            "lema": "espa\u00f1a",
            "pos": "NP00G00",
            "prob": "1"
        },
        {
            "word": ".",
            "lema": ".",
            "pos": "Fp",
            "prob": "1"
        },
        {
            "word": "Por",
            "lema": "por",
            "pos": "SP",
            "prob": "1"
        },
        {
            "word": "eso",
            "lema": "ese",
            "pos": "PD00S00",
            "prob": "1"
        },
        {
            "word": ",",
            "lema": ",",
            "pos": "Fc",
            "prob": "1"
        },
        {
            "word": "hoy",
            "lema": "hoy",
            "pos": "RG",
            "prob": "0.993864"
        },
        {
            "word": "es",
            "lema": "ser",
            "pos": "VSIP3S0",
            "prob": "1"
        },
        {
            "word": "un",
            "lema": "uno",
            "pos": "DI0MS0",
            "prob": "0.99698"
        },
        {
            "word": "deber",
            "lema": "deber",
            "pos": "NCMS000",
            "prob": "0.880435"
        },
        {
            "word": "de",
            "lema": "de",
            "pos": "SP",
            "prob": "0.999961"
        },
        {
            "word": "justicia",
            "lema": "justicia",
            "pos": "NCFS000",
            "prob": "1"
        },
        {
            "word": "pedir",
            "lema": "pedir",
            "pos": "VMN0000",
            "prob": "1"
        },
        {
            "word": "a",
            "lema": "a",
            "pos": "SP",
            "prob": "0.998775"
        },
        {
            "word": "quienes",
            "lema": "quien",
            "pos": "PR0CP00",
            "prob": "1"
        },
        {
            "word": "no",
            "lema": "no",
            "pos": "RN",
            "prob": "0.999297"
        },
        {
            "word": "est\u00e1n",
            "lema": "estar",
            "pos": "VMIP3P0",
            "prob": "0.99949"
        },
        {
            "word": "en",
            "lema": "en",
            "pos": "SP",
            "prob": "1"
        },
        {
            "word": "condiciones",
            "lema": "condici\u00f3n",
            "pos": "NCFP000",
            "prob": "0.998418"
        },
        {
            "word": "de",
            "lema": "de",
            "pos": "SP",
            "prob": "0.999961"
        },
        {
            "word": "liderar",
            "lema": "liderar",
            "pos": "VMN0000",
            "prob": "1"
        },
        {
            "word": "la",
            "lema": "el",
            "pos": "DA0FS0",
            "prob": "0.98926"
        },
        {
            "word": "reconstrucci\u00f3n",
            "lema": "reconstrucci\u00f3n",
            "pos": "NCFS000",
            "prob": "1"
        },
        {
            "word": "que",
            "lema": "que",
            "pos": "PR0CN00",
            "prob": "0.550139"
        },
        {
            "word": "se",
            "lema": "se",
            "pos": "P00CN00",
            "prob": "0.494509"
        },
        {
            "word": "vayan",
            "lema": "ir",
            "pos": "VMSP3P0",
            "prob": "0.986111"
        },
        {
            "word": ",",
            "lema": ",",
            "pos": "Fc",
            "prob": "1"
        },
        {
            "word": "y",
            "lema": "y",
            "pos": "CC",
            "prob": "0.999989"
        },
        {
            "word": "ese",
            "lema": "ese",
            "pos": "DD0MS0",
            "prob": "0.966694"
        },
        {
            "word": "sacrificio",
            "lema": "sacrificio",
            "pos": "NCMS000",
            "prob": "1"
        },
        {
            "word": "ser\u00e1",
            "lema": "ser",
            "pos": "VSIF3S0",
            "prob": "1"
        },
        {
            "word": "el",
            "lema": "el",
            "pos": "DA0MS0",
            "prob": "1"
        },
        {
            "word": "que",
            "lema": "que",
            "pos": "PR0CN00",
            "prob": "0.550139"
        },
        {
            "word": "mejor",
            "lema": "mejor",
            "pos": "RG",
            "prob": "0.212612"
        },
        {
            "word": "puedan",
            "lema": "poder",
            "pos": "VMSP3P0",
            "prob": "0.997382"
        },
        {
            "word": "rendir",
            "lema": "rendir",
            "pos": "VMN0000",
            "prob": "1"
        },
        {
            "word": "a",
            "lema": "a",
            "pos": "SP",
            "prob": "0.998775"
        },
        {
            "word": "Espa\u00f1a",
            "lema": "espa\u00f1a",
            "pos": "NP00G00",
            "prob": "1"
        },
        {
            "word": ".",
            "lema": ".",
            "pos": "Fp",
            "prob": "1"
        },
        {
            "word": "Muchas",
            "lema": "mucho",
            "pos": "DI0FP0",
            "prob": "0.82345"
        },
        {
            "word": "gracias",
            "lema": "gracia",
            "pos": "NCFP000",
            "prob": "1"
        },
        {
            "word": ".",
            "lema": ".",
            "pos": "Fp",
            "prob": "1"
        },
        {
            "word": "(",
            "lema": "(",
            "pos": "Fpa",
            "prob": "1"
        },
        {
            "word": "Aplausos",
            "lema": "aplausos",
            "pos": "NP00G00",
            "prob": "1"
        },
        {
            "word": ")",
            "lema": ")",
            "pos": "Fpt",
            "prob": "1"
        },
        {
            "word": ".",
            "lema": ".",
            "pos": "Fp",
            "prob": "1"
        }
    ]
}