{"id": "1276089272769134592", "lang": "es", "created_at": "2020-06-25T09:46:05.000Z", "text": "Todos los pol\u00edticos espa\u00f1oles deber\u00edamos coincidir en esta exigencia de @vox_es @Santi_ABASCAL \nDefender los intereses de Espa\u00f1a en Bruselas. https://t.co/sGgh0sVb1t", "diputado": {"apellidos": "S\u00e1ez Alonso-Mu\u00f1umer", "formacion": "Vox", "apellidosNombre": "S\u00e1ez Alonso-Mu\u00f1umer, Pablo", "fchBaja": "", "genero": 1, "fchAlta": "27/11/2019", "idLegislatura": 14, "grupo": "Grupo Parlamentario VOX", "idCircunscripcion": 47, "nombreCircunscripcion": "Valladolid", "nombre": "Pablo", "codParlamentario": 278, "twitter": "https://twitter.com/PabloSaezAM", "twitterUserName": "PabloSaezAM", "twitterUserId": "559273864"}}