{"id": "1292372503558529029", "text": "Hemos constru\u00eddo un s\u00f3lido escudo social y econ\u00f3mico para batallar contra el virus, pero esta lucha no ha impedido que la Agenda del gobierno de coalici\u00f3n haya ido avanzando. De hecho, ya hemos cumplido el 50% de los acuerdos.\n#BalanceGobierno #EnMarchaTodosUnidos https://t.co/ISRQ4eggl2", "created_at": "2020-08-09T08:09:50.000Z", "lang": "es", "diputado": {"apellidos": "Mart\u00ednez Seijo", "formacion": "PSOE", "apellidosNombre": "Mart\u00ednez Seijo, Mar\u00eda Luz", "fchBaja": "", "genero": 2, "fchAlta": "27/11/2019", "idLegislatura": 14, "grupo": "Grupo Parlamentario Socialista", "idCircunscripcion": 34, "nombreCircunscripcion": "Palencia", "nombre": "Mar\u00eda Luz", "codParlamentario": 251, "twitter": "https://twitter.com/luzseijo", "twitterUserName": "luzseijo", "twitterUserId": "270356445"}}