{"lang": "es", "id": "1300468678501314567", "created_at": "2020-08-31T16:21:09.000Z", "text": "Triste y preocupado por los #incendios que asolan Espa\u00f1a. Es duro ver nuestra tierra arrasada por las llamas, especialmente aquella a la que nos unen lazos personales, como en mi caso, #Huelva. Un abrazo a los afectados y a quienes luchan contra el fuego.\nhttps://t.co/1ZCnHLeuLL", "diputado": {"apellidos": "Bal Franc\u00e9s", "formacion": "Cs", "apellidosNombre": "Bal Franc\u00e9s, Edmundo", "fchBaja": "", "genero": 1, "fchAlta": "26/11/2019", "idLegislatura": 14, "grupo": "Grupo Parlamentario Ciudadanos", "idCircunscripcion": 28, "nombreCircunscripcion": "Madrid", "nombre": "Edmundo", "codParlamentario": 211, "twitter": "https://twitter.com/BalEdmundo", "twitterUserName": "BalEdmundo", "twitterUserId": "1099251922152931329"}}