{
    "created_at": "2020-09-11T12:12:12.000Z",
    "lang": "es",
    "text": "Fruct\u00edfero encuentro con el @alcaldemoronfra, Juanma Rodr\u00edguez, conociendo c\u00f3mo se implementan en Mor\u00f3n las medidas del Gobierno contra la crisis del #COVID19.\n\nNecesitamos Entidades Locales fuertes para dejar atr\u00e1s esta etapa aciaga y construir un futuro mejor para todos. https://t.co/tzlQnMKbtX",
    "id": "1304392296725610496",
    "diputado": {
        "apellidos": "Rodr\u00edguez G\u00f3mez de Celis",
        "formacion": "PSOE",
        "apellidosNombre": "Rodr\u00edguez G\u00f3mez de Celis, Alfonso",
        "fchBaja": "",
        "genero": 1,
        "fchAlta": "25/11/2019",
        "idLegislatura": 14,
        "grupo": "Grupo Parlamentario Socialista",
        "idCircunscripcion": 41,
        "nombreCircunscripcion": "Sevilla",
        "nombre": "Alfonso",
        "codParlamentario": 168,
        "twitter": "https://twitter.com/gomezdcelis",
        "twitterUserName": "gomezdcelis",
        "twitterUserId": "22473944"
    }
}