{"lang": "ca", "id": "1319312150704377858", "created_at": "2020-10-22T16:18:23.000Z", "text": "Gr\u00e0cies Presidenta, a tu i a tota la c\u00e0mara per l\u2019escalf \u2764\ufe0f https://t.co/yzkpghQgCx", "diputado": {"apellidos": "Vidal S\u00e1ez", "formacion": "ECP-GUAYEM EL CANVI", "apellidosNombre": "Vidal S\u00e1ez, Aina", "fchBaja": "", "genero": 2, "fchAlta": "27/11/2019", "idLegislatura": 14, "grupo": "Grupo Parlamentario Confederal de Unidas Podemos-En Com\u00fa Podem-Galicia en Com\u00fan", "idCircunscripcion": 8, "nombreCircunscripcion": "Barcelona", "nombre": "Aina", "codParlamentario": 266, "twitter": "https://twitter.com/AinaVS", "twitterUserName": "AinaVS", "twitterUserId": "53350394"}}