{"lang": "es", "id": "1326539158731452417", "created_at": "2020-11-11T14:55:56.000Z", "text": "Las bases pol\u00edticas de los Presupuestos que vienen:\n\nOtegi confirma el S\u00ed de Bildu, y Pablo Iglesias celebra la fuerza del bloque de investidura y la integraci\u00f3n de Bildu en \u201cla direcci\u00f3n del Estado\u201d", "diputado": {"apellidos": "Uriarte Bengoechea", "formacion": "PP", "apellidosNombre": "Uriarte Bengoechea, Edurne", "fchBaja": "", "genero": 2, "fchAlta": "19/11/2019", "idLegislatura": 14, "grupo": "Grupo Parlamentario Popular en el Congreso", "idCircunscripcion": 28, "nombreCircunscripcion": "Madrid", "nombre": "Edurne", "codParlamentario": 30, "twitter": "https://twitter.com/EdurneUriarte", "twitterUserName": "EdurneUriarte", "twitterUserId": "250092838"}}