{
    "lang": "es",
    "id": "1337711091309305856",
    "created_at": "2020-12-12T10:49:12.000Z",
    "text": "Su majestad, la Constituci\u00f3n ya le reconoc\u00eda a usted  la irresponsabilidad. No necesitaba usted demostrarla",
    "diputado": {
        "apellidos": "Uriarte Torrealday",
        "formacion": "UP",
        "apellidosNombre": "Uriarte Torrealday, Roberto",
        "fchBaja": "",
        "genero": 1,
        "fchAlta": "26/11/2019",
        "idLegislatura": 14,
        "grupo": "Grupo Parlamentario Confederal de Unidas Podemos-En Com\u00fa Podem-Galicia en Com\u00fan",
        "idCircunscripcion": 48,
        "nombreCircunscripcion": "Bizkaia",
        "nombre": "Roberto",
        "codParlamentario": 207,
        "twitter": "https://twitter.com/RoberUriarte",
        "twitterUserName": "RoberUriarte",
        "twitterUserId": "3019568698"
    },
    "freeling": [
        {
            "word": "Su",
            "lema": "su",
            "pos": "DP3CSN",
            "prob": "1"
        },
        {
            "word": "majestad",
            "lema": "majestad",
            "pos": "NCFS000",
            "prob": "1"
        },
        {
            "word": ",",
            "lema": ",",
            "pos": "Fc",
            "prob": "1"
        },
        {
            "word": "la",
            "lema": "el",
            "pos": "DA0FS0",
            "prob": "0.98926"
        },
        {
            "word": "Constituci\u00f3n",
            "lema": "constituci\u00f3n",
            "pos": "NP00V00",
            "prob": "1"
        },
        {
            "word": "ya",
            "lema": "ya",
            "pos": "RG",
            "prob": "0.999785"
        },
        {
            "word": "le",
            "lema": "le",
            "pos": "PP3CSD0",
            "prob": "1"
        },
        {
            "word": "reconoc\u00eda",
            "lema": "reconocer",
            "pos": "VMII3S0",
            "prob": "0.65"
        },
        {
            "word": "a",
            "lema": "a",
            "pos": "SP",
            "prob": "0.998775"
        },
        {
            "word": "usted",
            "lema": "usted",
            "pos": "PP2CS0P",
            "prob": "1"
        },
        {
            "word": "la",
            "lema": "el",
            "pos": "DA0FS0",
            "prob": "0.98926"
        },
        {
            "word": "irresponsabilidad",
            "lema": "irresponsabilidad",
            "pos": "NCFS000",
            "prob": "1"
        },
        {
            "word": ".",
            "lema": ".",
            "pos": "Fp",
            "prob": "1"
        },
        {
            "word": "No",
            "lema": "no",
            "pos": "RN",
            "prob": "0.999297"
        },
        {
            "word": "necesitaba",
            "lema": "necesitar",
            "pos": "VMII3S0",
            "prob": "0.65"
        },
        {
            "word": "usted",
            "lema": "usted",
            "pos": "PP2CS0P",
            "prob": "1"
        },
        {
            "word": "demostrar",
            "lema": "demostrar",
            "pos": "VMN0000",
            "prob": "1"
        },
        {
            "word": "la",
            "lema": "lo",
            "pos": "PP3FSA0",
            "prob": "1"
        },
        {
            "word": ".",
            "lema": ".",
            "pos": "Fp",
            "prob": "1"
        }
    ]
}