{
    "created_at": "2021-02-24T17:23:20.000Z",
    "lang": "es",
    "text": "Vistas las reacciones de la ultraderecha, deben creer que \u201ctecho de cristal\u201d y \u201csuelo pegajoso\u201d son dos superzings.\nVaya nivel. \ud83e\udd26\ud83c\udffe\u200d\u2640\ufe0f",
    "id": "1364626981510381571",
    "diputado": {
        "apellidos": "Fern\u00e1ndez Casta\u00f1\u00f3n",
        "formacion": "UP",
        "apellidosNombre": "Fern\u00e1ndez Casta\u00f1\u00f3n, Sof\u00eda",
        "fchBaja": "",
        "genero": 2,
        "fchAlta": "27/11/2019",
        "idLegislatura": 14,
        "grupo": "Grupo Parlamentario Confederal de Unidas Podemos-En Com\u00fa Podem-Galicia en Com\u00fan",
        "idCircunscripcion": 33,
        "nombreCircunscripcion": "Asturias",
        "nombre": "Sof\u00eda",
        "codParlamentario": 272,
        "twitter": "https://twitter.com/SofCastanon",
        "twitterUserName": "SofCastanon",
        "twitterUserId": "3495603017"
    },
    "freeling": [
        {
            "word": "Vistas",
            "lema": "ver",
            "pos": "VMP00PF",
            "prob": "0.72093"
        },
        {
            "word": "las",
            "lema": "el",
            "pos": "DA0FP0",
            "prob": "0.988184"
        },
        {
            "word": "reacciones",
            "lema": "reacci\u00f3n",
            "pos": "NCFP000",
            "prob": "0.983871"
        },
        {
            "word": "de",
            "lema": "de",
            "pos": "SP",
            "prob": "0.999961"
        },
        {
            "word": "la",
            "lema": "el",
            "pos": "DA0FS0",
            "prob": "0.98926"
        },
        {
            "word": "ultraderecha",
            "lema": "ultraderecha",
            "pos": "NCFS000",
            "prob": "1"
        },
        {
            "word": ",",
            "lema": ",",
            "pos": "Fc",
            "prob": "1"
        },
        {
            "word": "deben",
            "lema": "deber",
            "pos": "VMIP3P0",
            "prob": "1"
        },
        {
            "word": "creer",
            "lema": "creer",
            "pos": "VMN0000",
            "prob": "1"
        },
        {
            "word": "que",
            "lema": "que",
            "pos": "CS",
            "prob": "0.449861"
        },
        {
            "word": "\u201c",
            "lema": "\u201c",
            "pos": "Fra",
            "prob": "1"
        },
        {
            "word": "techo",
            "lema": "techo",
            "pos": "NCMS000",
            "prob": "0.986111"
        },
        {
            "word": "de",
            "lema": "de",
            "pos": "SP",
            "prob": "0.999961"
        },
        {
            "word": "cristal",
            "lema": "cristal",
            "pos": "NCMS000",
            "prob": "1"
        },
        {
            "word": "\u201d",
            "lema": "\u201d",
            "pos": "Frc",
            "prob": "1"
        },
        {
            "word": "y",
            "lema": "y",
            "pos": "CC",
            "prob": "0.999989"
        },
        {
            "word": "\u201c",
            "lema": "\u201c",
            "pos": "Fra",
            "prob": "1"
        },
        {
            "word": "suelo",
            "lema": "suelo",
            "pos": "NCMS000",
            "prob": "0.88102"
        },
        {
            "word": "pegajoso",
            "lema": "pegajoso",
            "pos": "AQ0MS00",
            "prob": "1"
        },
        {
            "word": "\u201d",
            "lema": "\u201d",
            "pos": "Frc",
            "prob": "1"
        },
        {
            "word": "son",
            "lema": "ser",
            "pos": "VSIP3P0",
            "prob": "0.995197"
        },
        {
            "word": "dos",
            "lema": "2",
            "pos": "Z",
            "prob": "0.999868"
        },
        {
            "word": "superzings",
            "lema": "superzings",
            "pos": "NCMP000",
            "prob": "1"
        },
        {
            "word": ".",
            "lema": ".",
            "pos": "Fp",
            "prob": "1"
        },
        {
            "word": "Vaya",
            "lema": "ir",
            "pos": "VMM03S0",
            "prob": "0.217021"
        },
        {
            "word": "nivel",
            "lema": "nivel",
            "pos": "NCMS000",
            "prob": "1"
        },
        {
            "word": ".",
            "lema": ".",
            "pos": "Fp",
            "prob": "1"
        },
        {
            "word": "\ud83e\udd26",
            "lema": "\ud83e\udd26",
            "pos": "Fz",
            "prob": "1"
        },
        {
            "word": "\ud83c\udffe",
            "lema": "\ud83c\udffe",
            "pos": "Fz",
            "prob": "1"
        },
        {
            "word": "\u200d",
            "lema": "\u200d",
            "pos": "Fz",
            "prob": "1"
        },
        {
            "word": "\u2640",
            "lema": "\u2640",
            "pos": "Fz",
            "prob": "1"
        },
        {
            "word": "\ufe0f",
            "lema": "\ufe0f",
            "pos": "Fz",
            "prob": "1"
        },
        {
            "word": ".",
            "lema": ".",
            "pos": "Fp",
            "prob": "1"
        }
    ]
}