{
    "text": "Honrado por participar en el libro colectivo \n\n\u201cLARGO CABALLERO: UN DEBER DE MEMORIA\u201d\n\nGracias a @LmReillo y @UGTMadrid por contar conmigo https://t.co/DktFflVHxp",
    "id": "1365984460165050368",
    "lang": "es",
    "created_at": "2021-02-28T11:17:28.000Z",
    "diputado": {
        "apellidos": "Simancas Simancas",
        "formacion": "PSOE",
        "apellidosNombre": "Simancas Simancas, Rafael",
        "fchBaja": "",
        "genero": 1,
        "fchAlta": "27/11/2019",
        "idLegislatura": 14,
        "grupo": "Grupo Parlamentario Socialista",
        "idCircunscripcion": 28,
        "nombreCircunscripcion": "Madrid",
        "nombre": "Rafael",
        "codParlamentario": 287,
        "twitter": "https://twitter.com/SimancasRafael",
        "twitterUserName": "SimancasRafael",
        "twitterUserId": "402219133"
    }
}