{"id": "1369368119941214212", "lang": "es", "created_at": "2021-03-09T19:22:56.000Z", "text": "2/2 En la ultima PNL que defend\u00ed en el Congreso, el ultimo punto de la misma solicitaba precisamente esto, por desgracia fue rechazada con el voto en contra de PSOE, Podemos, PNV o Esquerra Republicana. Ma\u00f1ana mismo desde el @GPPopular seguiremos exigiendo que se les incluya. https://t.co/J0lnYbaBeP", "diputado": {"apellidos": "Almod\u00f3bar Barcel\u00f3", "formacion": "PP", "apellidosNombre": "Almod\u00f3bar Barcel\u00f3, Agust\u00edn", "fchBaja": "", "genero": 1, "fchAlta": "28/11/2019", "idLegislatura": 14, "grupo": "Grupo Parlamentario Popular en el Congreso", "idCircunscripcion": 3, "nombreCircunscripcion": "Alicante/Alacant", "nombre": "Agust\u00edn", "codParlamentario": 305, "twitter": "https://twitter.com/aalmodobar", "twitterUserName": "aalmodobar", "twitterUserId": "155350950"}}